nemo_text_processing/__init__.py
nemo_text_processing/package_info.py
nemo_text_processing/fst_alignment/__init__.py
nemo_text_processing/fst_alignment/alignment.py
nemo_text_processing/g2p/__init__.py
nemo_text_processing/g2p/data/__init__.py
nemo_text_processing/hybrid/__init__.py
nemo_text_processing/hybrid/mlm_scorer.py
nemo_text_processing/hybrid/model_utils.py
nemo_text_processing/hybrid/utils.py
nemo_text_processing/hybrid/wfst_lm_rescoring.py
nemo_text_processing/inverse_text_normalization/__init__.py
nemo_text_processing/inverse_text_normalization/inverse_normalize.py
nemo_text_processing/inverse_text_normalization/run_evaluate.py
nemo_text_processing/inverse_text_normalization/ar/__init__.py
nemo_text_processing/inverse_text_normalization/ar/utils.py
nemo_text_processing/inverse_text_normalization/ar/taggers/__init__.py
nemo_text_processing/inverse_text_normalization/ar/taggers/cardinal.py
nemo_text_processing/inverse_text_normalization/ar/taggers/decimal.py
nemo_text_processing/inverse_text_normalization/ar/taggers/fraction.py
nemo_text_processing/inverse_text_normalization/ar/taggers/measure.py
nemo_text_processing/inverse_text_normalization/ar/taggers/money.py
nemo_text_processing/inverse_text_normalization/ar/taggers/punctuation.py
nemo_text_processing/inverse_text_normalization/ar/taggers/tokenize_and_classify.py
nemo_text_processing/inverse_text_normalization/ar/taggers/word.py
nemo_text_processing/inverse_text_normalization/ar/verbalizers/__init__.py
nemo_text_processing/inverse_text_normalization/ar/verbalizers/cardinal.py
nemo_text_processing/inverse_text_normalization/ar/verbalizers/decimal.py
nemo_text_processing/inverse_text_normalization/ar/verbalizers/fraction.py
nemo_text_processing/inverse_text_normalization/ar/verbalizers/measure.py
nemo_text_processing/inverse_text_normalization/ar/verbalizers/money.py
nemo_text_processing/inverse_text_normalization/ar/verbalizers/verbalize.py
nemo_text_processing-1.1.0.dist-info/LICENSE
nemo_text_processing-1.1.0.dist-info/METADATA
nemo_text_processing-1.1.0.dist-info/WHEEL
nemo_text_processing-1.1.0.dist-info/top_level.txt
nemo_text_processing-1.1.0.dist-info/RECORD
