Metadata-Version: 2.1
Name: nemo_text_processing
Version: 1.1.0
Summary: NeMo text processing for ASR and TTS
Home-page: https://github.com/nvidia/nemo-text-processing
Download-URL: https://github.com/NVIDIA/NeMo-text-processing/releases
Author: NVIDIA
Author-email: nemo-toolkit@nvidia.com
Maintainer: NVIDIA
Maintainer-email: nemo-toolkit@nvidia.com
License: Apache2
Keywords: NeMo,nvidia,tts,asr,text processing,text normalization,inverse text normalization,language
Classifier: Development Status :: 5 - Production/Stable
Classifier: Intended Audience :: Developers
Classifier: Intended Audience :: Science/Research
Classifier: Intended Audience :: Information Technology
Classifier: Topic :: Scientific/Engineering
Classifier: Topic :: Scientific/Engineering :: Mathematics
Classifier: Topic :: Scientific/Engineering :: Image Recognition
Classifier: Topic :: Scientific/Engineering :: Artificial Intelligence
Classifier: Topic :: Software Development :: Libraries
Classifier: Topic :: Software Development :: Libraries :: Python Modules
Classifier: Topic :: Utilities
Classifier: License :: OSI Approved :: Apache Software License
Classifier: Programming Language :: Python :: 3
Classifier: Programming Language :: Python :: 3.8
Classifier: Programming Language :: Python :: 3.9
Classifier: Environment :: Console
Classifier: Natural Language :: English
Classifier: Operating System :: OS Independent
License-File: LICENSE
Requires-Dist: cdifflib
Requires-Dist: editdistance
Requires-Dist: inflect
Requires-Dist: joblib
Requires-Dist: pandas
Requires-Dist: pynini ==2.1.6.post1
Requires-Dist: regex
Requires-Dist: sacremoses >=0.0.43
Requires-Dist: setuptools >=65.5.1
Requires-Dist: tqdm >=4.41.0
Requires-Dist: transformers
Requires-Dist: wget
Requires-Dist: wrapt
Provides-Extra: all
Requires-Dist: black ==19.10b0 ; extra == 'all'
Requires-Dist: click ==8.0.2 ; extra == 'all'
Requires-Dist: isort[requirements] <6.0.0,>5.1.0 ; extra == 'all'
Requires-Dist: parameterized ; extra == 'all'
Requires-Dist: pynini ==2.1.6.post1 ; extra == 'all'
Requires-Dist: pytest ; extra == 'all'
Requires-Dist: pytest-runner ; extra == 'all'
Requires-Dist: ruamel.yaml ; extra == 'all'
Requires-Dist: sphinx ; extra == 'all'
Requires-Dist: sphinxcontrib-bibtex ; extra == 'all'
Requires-Dist: wandb ; extra == 'all'
Requires-Dist: wget ; extra == 'all'
Requires-Dist: wrapt ; extra == 'all'
Provides-Extra: test
Requires-Dist: black ==19.10b0 ; extra == 'test'
Requires-Dist: click ==8.0.2 ; extra == 'test'
Requires-Dist: isort[requirements] <6.0.0,>5.1.0 ; extra == 'test'
Requires-Dist: parameterized ; extra == 'test'
Requires-Dist: pynini ==2.1.6.post1 ; extra == 'test'
Requires-Dist: pytest ; extra == 'test'
Requires-Dist: pytest-runner ; extra == 'test'
Requires-Dist: ruamel.yaml ; extra == 'test'
Requires-Dist: sphinx ; extra == 'test'
Requires-Dist: sphinxcontrib-bibtex ; extra == 'test'
Requires-Dist: wandb ; extra == 'test'
Requires-Dist: wget ; extra == 'test'
Requires-Dist: wrapt ; extra == 'test'
